django_states/__init__.py
django_states/compat.py
django_states/conf.py
django_states/exceptions.py
django_states/fields.py
django_states/log.py
django_states/machine.py
django_states/model_methods.py
django_states/models.py
django_states/signals.py
django_states/tests.py
django_states/urls.py
django_states/views.py
django_states/management/__init__.py
django_states/management/commands/__init__.py
django_states/management/commands/graph_states2.py
django_states/templatetags/__init__.py
django_states/templatetags/django_states.py
pivotal_django_states-1.6.14.dist-info/LICENSE.txt
pivotal_django_states-1.6.14.dist-info/METADATA
pivotal_django_states-1.6.14.dist-info/RECORD
pivotal_django_states-1.6.14.dist-info/WHEEL
pivotal_django_states-1.6.14.dist-info/top_level.txt
