Metadata-Version: 2.1
Name: pivotal-django-states
Version: 1.6.14
Summary: State machine for django models
Home-page: https://github.com/pivotal-energy-solutions/django-states2
Author: Pivotal Energy Solutions
Author-email: sklass@pivotalenergysolutions.com
License: UNKNOWN
Download-URL: https://github.com/pivotal-energy-solutions/django-states2/archive/1.6.14.tar.gz
Project-URL: Bug Reports, https://github.com/pivotal-energy-solutions/django-states2/issues
Project-URL: Say Thanks!, https://saythanks.io/to/rh0dium
Project-URL: Original Source, https://github.com/vikingco/django-states2
Keywords: django state-machine
Platform: UNKNOWN
Classifier: Development Status :: 5 - Production/Stable
Classifier: Intended Audience :: Developers
Classifier: License :: OSI Approved :: MIT License
Classifier: Programming Language :: Python :: 2
Classifier: Programming Language :: Python :: 2.7
Classifier: Operating System :: OS Independent
Classifier: Environment :: Web Environment
Classifier: Framework :: Django
Requires-Dist: django (<2.0,>=1.11)
